LICENSE.txt
README.md
setup.cfg
setup.py
Topsis_Gurleen_102003138/__init__.py
Topsis_Gurleen_102003138/topsis_102003138.py
topsis_Gurleen_102003138.egg-info/PKG-INFO
topsis_Gurleen_102003138.egg-info/SOURCES.txt
topsis_Gurleen_102003138.egg-info/dependency_links.txt
topsis_Gurleen_102003138.egg-info/requires.txt
topsis_Gurleen_102003138.egg-info/top_level.txt