Metadata-Version: 2.1
Name: topsis-Gurleen-102003138
Version: 0.1
Summary: This package is implementation of Multiple-criteria decision making using Topsis Algorithm
Home-page: https://github.com/Gurleen21
Download-URL: https://github.com/Gurleen21/Topsis_Gurleen_102003138.git
Author: Gurleen Kaur
Author-email: gurleen2113@gmail.com
License: MIT
Keywords: TOPSIS,MULTIPLE CRITERIA DECISION MAKING,MCDM
Classifier: Development Status :: 3 - Alpha
Classifier: Topic :: Software Development :: Build Tools
Classifier: License :: OSI Approved :: MIT License
Classifier: Programming Language :: Python :: 3.8
Classifier: Programming Language :: Python :: 3.9
Classifier: Programming Language :: Python :: 3.10
Classifier: Programming Language :: Python :: 3.11
License-File: LICENSE.txt
